picoapi/__init__.py
picoapi/__main__.py
picoapi/api.py
picoapi/healthcheck.py
picoapi/schema.py
picoapi-1.0.4.dist-info/LICENSE
picoapi-1.0.4.dist-info/METADATA
picoapi-1.0.4.dist-info/WHEEL
picoapi-1.0.4.dist-info/top_level.txt
picoapi-1.0.4.dist-info/RECORD
