Metadata-Version: 2.1
Name: picoapi
Version: 1.0.4
Summary: An opinionated wrapper around FastAPI with custom microservice registration
Home-page: https://github.com/schlerp/picoapi
Author: Patrick Coffey
Author-email: patrickcoffey91@gmail.com
License: UNKNOWN
Platform: UNKNOWN
Classifier: Programming Language :: Python :: 3
Classifier: License :: OSI Approved :: BSD License
Classifier: Operating System :: OS Independent
Requires-Python: >=3.6
Requires-Dist: pydantic
Requires-Dist: fastapi
Requires-Dist: requests
